[
    {
        "%vlocity_namespace%__DomainObjectAPIName__c": "Formula",
        "%vlocity_namespace%__DomainObjectCreationOrder__c": 0,
        "%vlocity_namespace%__DomainObjectFieldAPIName__c": "Formula",
        "%vlocity_namespace%__FormulaOrder__c": 1,
        "%vlocity_namespace%__FormulaResultPath__c": "Pricing-Pricelist Entries:Qualification Context Rule Set Assignment Name",
        "%vlocity_namespace%__Formula__c": "CONCAT(var:\"Pricing-Pricelist Entries:Offering\", \"-\", var:\"Pricing-Pricelist Entries:Qualification Context Rule Set\")",
        "%vlocity_namespace%__GlobalKey__c": "903115e3-d088-2dbf-cbd5-4c709216cfe6",
        "%vlocity_namespace%__IsDisabled__c": false,
        "%vlocity_namespace%__IsRequiredForUpsert__c": false,
        "%vlocity_namespace%__MapId__c": "EOSLoadPricingPricelistEntries6783767996725447",
        "%vlocity_namespace%__OMplusSyncEnabled__c": true,
        "%vlocity_namespace%__UpsertKey__c": false,
        "IsLocked": false,
        "MayEdit": true,
        "Name": "EOSLoadPricingPricelistEntries",
        "VlocityDataPackType": "SObject",
        "VlocityRecordSObjectType": "%vlocity_namespace%__DRMapItem__c"
    },
    {
        "%vlocity_namespace%__DomainObjectAPIName__c": "%vlocity_namespace%__PriceListEntry__c",
        "%vlocity_namespace%__DomainObjectCreationOrder__c": 1,
        "%vlocity_namespace%__DomainObjectFieldAPIName__c": "%vlocity_namespace%__DisplayText__c",
        "%vlocity_namespace%__GlobalKey__c": "c934c133-57d2-620e-145e-d8eca3d679c5",
        "%vlocity_namespace%__InterfaceFieldAPIName__c": "Pricing-Pricelist Entries:Display Text",
        "%vlocity_namespace%__IsDisabled__c": false,
        "%vlocity_namespace%__IsRequiredForUpsert__c": true,
        "%vlocity_namespace%__MapId__c": "EOSLoadPricingPricelistEntries5864993301893229",
        "%vlocity_namespace%__OMplusSyncEnabled__c": true,
        "%vlocity_namespace%__UpsertKey__c": false,
        "IsLocked": false,
        "MayEdit": true,
        "Name": "EOSLoadPricingPricelistEntries",
        "VlocityDataPackType": "SObject",
        "VlocityRecordSObjectType": "%vlocity_namespace%__DRMapItem__c"
    },
    {
        "%vlocity_namespace%__DomainObjectAPIName__c": "%vlocity_namespace%__PriceListEntry__c",
        "%vlocity_namespace%__DomainObjectCreationOrder__c": 1,
        "%vlocity_namespace%__DomainObjectFieldAPIName__c": "%vlocity_namespace%__EffectiveFromDate__c",
        "%vlocity_namespace%__GlobalKey__c": "b3414836-06fc-e31e-402b-7cb21369045b",
        "%vlocity_namespace%__InterfaceFieldAPIName__c": "Pricing-Pricelist Entries:Effective Start Date",
        "%vlocity_namespace%__IsDisabled__c": false,
        "%vlocity_namespace%__IsRequiredForUpsert__c": false,
        "%vlocity_namespace%__MapId__c": "EOSLoadPricingPricelistEntries32144587196774554",
        "%vlocity_namespace%__OMplusSyncEnabled__c": true,
        "%vlocity_namespace%__UpsertKey__c": false,
        "IsLocked": false,
        "MayEdit": true,
        "Name": "EOSLoadPricingPricelistEntries",
        "VlocityDataPackType": "SObject",
        "VlocityRecordSObjectType": "%vlocity_namespace%__DRMapItem__c"
    },
    {
        "%vlocity_namespace%__DomainObjectAPIName__c": "%vlocity_namespace%__PriceListEntry__c",
        "%vlocity_namespace%__DomainObjectCreationOrder__c": 1,
        "%vlocity_namespace%__DomainObjectFieldAPIName__c": "%vlocity_namespace%__EffectiveUntilDate__c",
        "%vlocity_namespace%__GlobalKey__c": "71418cc3-bc60-6eb0-8119-014fabd6f961",
        "%vlocity_namespace%__InterfaceFieldAPIName__c": "Pricing-Pricelist Entries:Effective End Date",
        "%vlocity_namespace%__IsDisabled__c": false,
        "%vlocity_namespace%__IsRequiredForUpsert__c": false,
        "%vlocity_namespace%__MapId__c": "EOSLoadPricingPricelistEntries7515231389791597",
        "%vlocity_namespace%__OMplusSyncEnabled__c": true,
        "%vlocity_namespace%__UpsertKey__c": false,
        "IsLocked": false,
        "MayEdit": true,
        "Name": "EOSLoadPricingPricelistEntries",
        "VlocityDataPackType": "SObject",
        "VlocityRecordSObjectType": "%vlocity_namespace%__DRMapItem__c"
    },
    {
        "%vlocity_namespace%__DefaultValue__c": "true",
        "%vlocity_namespace%__DomainObjectAPIName__c": "%vlocity_namespace%__PriceListEntry__c",
        "%vlocity_namespace%__DomainObjectCreationOrder__c": 1,
        "%vlocity_namespace%__DomainObjectFieldAPIName__c": "%vlocity_namespace%__IsActive__c",
        "%vlocity_namespace%__GlobalKey__c": "3f122be5-482a-4352-4c01-6b101f19f4bd",
        "%vlocity_namespace%__InterfaceFieldAPIName__c": "Pricing-Pricelist Entries:Active",
        "%vlocity_namespace%__IsDisabled__c": false,
        "%vlocity_namespace%__IsRequiredForUpsert__c": false,
        "%vlocity_namespace%__MapId__c": "EOSLoadPricingPricelistEntries2862081357401556",
        "%vlocity_namespace%__OMplusSyncEnabled__c": true,
        "%vlocity_namespace%__TransformValuesMap__c": "{\"Yes\":\"true\",\"No\":\"fals\"}",
        "%vlocity_namespace%__UpsertKey__c": false,
        "IsLocked": false,
        "MayEdit": true,
        "Name": "EOSLoadPricingPricelistEntries",
        "VlocityDataPackType": "SObject",
        "VlocityRecordSObjectType": "%vlocity_namespace%__DRMapItem__c"
    },
    {
        "%vlocity_namespace%__DefaultValue__c": "false",
        "%vlocity_namespace%__DomainObjectAPIName__c": "%vlocity_namespace%__PriceListEntry__c",
        "%vlocity_namespace%__DomainObjectCreationOrder__c": 1,
        "%vlocity_namespace%__DomainObjectFieldAPIName__c": "%vlocity_namespace%__IsBasePrice__c",
        "%vlocity_namespace%__GlobalKey__c": "71a8e5f8-f7cf-ac89-3ca2-a85397425559",
        "%vlocity_namespace%__InterfaceFieldAPIName__c": "Pricing-Pricelist Entries:Base Price",
        "%vlocity_namespace%__IsDisabled__c": false,
        "%vlocity_namespace%__IsRequiredForUpsert__c": false,
        "%vlocity_namespace%__MapId__c": "EOSLoadPricingPricelistEntries6627692135739911",
        "%vlocity_namespace%__OMplusSyncEnabled__c": true,
        "%vlocity_namespace%__TransformValuesMap__c": "{}",
        "%vlocity_namespace%__UpsertKey__c": false,
        "IsLocked": false,
        "MayEdit": true,
        "Name": "EOSLoadPricingPricelistEntries",
        "VlocityDataPackType": "SObject",
        "VlocityRecordSObjectType": "%vlocity_namespace%__DRMapItem__c"
    },
    {
        "%vlocity_namespace%__DefaultValue__c": "false",
        "%vlocity_namespace%__DomainObjectAPIName__c": "%vlocity_namespace%__PriceListEntry__c",
        "%vlocity_namespace%__DomainObjectCreationOrder__c": 1,
        "%vlocity_namespace%__DomainObjectFieldAPIName__c": "%vlocity_namespace%__IsVirtualPrice__c",
        "%vlocity_namespace%__GlobalKey__c": "278de6a9-a229-890a-6218-a14ba5a387e9",
        "%vlocity_namespace%__InterfaceFieldAPIName__c": "Pricing-Pricelist Entries:Virtual Price",
        "%vlocity_namespace%__IsDisabled__c": false,
        "%vlocity_namespace%__IsRequiredForUpsert__c": false,
        "%vlocity_namespace%__MapId__c": "EOSLoadPricingPricelistEntries01991807202097373",
        "%vlocity_namespace%__OMplusSyncEnabled__c": true,
        "%vlocity_namespace%__TransformValuesMap__c": "{}",
        "%vlocity_namespace%__UpsertKey__c": false,
        "IsLocked": false,
        "MayEdit": true,
        "Name": "EOSLoadPricingPricelistEntries",
        "VlocityDataPackType": "SObject",
        "VlocityRecordSObjectType": "%vlocity_namespace%__DRMapItem__c"
    },
    {
        "%vlocity_namespace%__DomainObjectAPIName__c": "%vlocity_namespace%__PriceListEntry__c",
        "%vlocity_namespace%__DomainObjectCreationOrder__c": 1,
        "%vlocity_namespace%__DomainObjectFieldAPIName__c": "%vlocity_namespace%__PriceListId__c",
        "%vlocity_namespace%__GlobalKey__c": "ba068fb6-c7c9-7a24-8dab-d506f3e22a53",
        "%vlocity_namespace%__InterfaceFieldAPIName__c": "Pricing-Pricelist Entries:Pricelist Code",
        "%vlocity_namespace%__IsDisabled__c": false,
        "%vlocity_namespace%__IsRequiredForUpsert__c": true,
        "%vlocity_namespace%__LookupDomainObjectFieldName__c": "%vlocity_namespace%__Code__c",
        "%vlocity_namespace%__LookupDomainObjectName__c": "%vlocity_namespace%__PriceList__c",
        "%vlocity_namespace%__LookupDomainObjectRequestedFieldName__c": "Id",
        "%vlocity_namespace%__MapId__c": "EOSLoadPricingPricelistEntries015397153451207624",
        "%vlocity_namespace%__OMplusSyncEnabled__c": true,
        "%vlocity_namespace%__UpsertKey__c": true,
        "IsLocked": false,
        "MayEdit": true,
        "Name": "EOSLoadPricingPricelistEntries",
        "VlocityDataPackType": "SObject",
        "VlocityRecordSObjectType": "%vlocity_namespace%__DRMapItem__c"
    },
    {
        "%vlocity_namespace%__DomainObjectAPIName__c": "%vlocity_namespace%__PriceListEntry__c",
        "%vlocity_namespace%__DomainObjectCreationOrder__c": 1,
        "%vlocity_namespace%__DomainObjectFieldAPIName__c": "%vlocity_namespace%__PricingElementId__c",
        "%vlocity_namespace%__GlobalKey__c": "9601f56c-075a-5ffa-0bfc-5fec68e1f19d",
        "%vlocity_namespace%__InterfaceFieldAPIName__c": "Pricing-Pricelist Entries:Pricelist Code",
        "%vlocity_namespace%__IsDisabled__c": false,
        "%vlocity_namespace%__IsRequiredForUpsert__c": false,
        "%vlocity_namespace%__LookupDomainObjectFieldName__c": "%vlocity_namespace%__PriceListId__r.%vlocity_namespace%__Code__c",
        "%vlocity_namespace%__LookupDomainObjectName__c": "%vlocity_namespace%__PricingElement__c",
        "%vlocity_namespace%__LookupDomainObjectRequestedFieldName__c": "Id",
        "%vlocity_namespace%__MapId__c": "EOSLoadPricingPricelistEntries6377836045239935",
        "%vlocity_namespace%__OMplusSyncEnabled__c": true,
        "%vlocity_namespace%__UpsertKey__c": false,
        "IsLocked": false,
        "MayEdit": true,
        "Name": "EOSLoadPricingPricelistEntries",
        "VlocityDataPackType": "SObject",
        "VlocityRecordSObjectType": "%vlocity_namespace%__DRMapItem__c"
    },
    {
        "%vlocity_namespace%__DomainObjectAPIName__c": "%vlocity_namespace%__PriceListEntry__c",
        "%vlocity_namespace%__DomainObjectCreationOrder__c": 1,
        "%vlocity_namespace%__DomainObjectFieldAPIName__c": "%vlocity_namespace%__PricingElementId__c",
        "%vlocity_namespace%__GlobalKey__c": "3b37dc8d-850f-38df-dee3-d76cea93192f",
        "%vlocity_namespace%__InterfaceFieldAPIName__c": "Pricing-Pricelist Entries:Pricing Element",
        "%vlocity_namespace%__IsDisabled__c": false,
        "%vlocity_namespace%__IsRequiredForUpsert__c": true,
        "%vlocity_namespace%__LookupDomainObjectFieldName__c": "Name",
        "%vlocity_namespace%__LookupDomainObjectName__c": "%vlocity_namespace%__PricingElement__c",
        "%vlocity_namespace%__LookupDomainObjectRequestedFieldName__c": "Id",
        "%vlocity_namespace%__MapId__c": "EOSLoadPricingPricelistEntries9913298326778406",
        "%vlocity_namespace%__OMplusSyncEnabled__c": true,
        "%vlocity_namespace%__UpsertKey__c": true,
        "IsLocked": false,
        "MayEdit": true,
        "Name": "EOSLoadPricingPricelistEntries",
        "VlocityDataPackType": "SObject",
        "VlocityRecordSObjectType": "%vlocity_namespace%__DRMapItem__c"
    },
    {
        "%vlocity_namespace%__DomainObjectAPIName__c": "%vlocity_namespace%__PriceListEntry__c",
        "%vlocity_namespace%__DomainObjectCreationOrder__c": 1,
        "%vlocity_namespace%__DomainObjectFieldAPIName__c": "%vlocity_namespace%__ProductId__c",
        "%vlocity_namespace%__GlobalKey__c": "08b794c2-d572-9f53-bb45-6e1fec46131c",
        "%vlocity_namespace%__InterfaceFieldAPIName__c": "Pricing-Pricelist Entries:Offering Code",
        "%vlocity_namespace%__IsDisabled__c": false,
        "%vlocity_namespace%__IsRequiredForUpsert__c": true,
        "%vlocity_namespace%__LookupDomainObjectFieldName__c": "ProductCode",
        "%vlocity_namespace%__LookupDomainObjectName__c": "Product2",
        "%vlocity_namespace%__LookupDomainObjectRequestedFieldName__c": "Id",
        "%vlocity_namespace%__MapId__c": "EOSLoadPricingPricelistEntries44586505584830727",
        "%vlocity_namespace%__OMplusSyncEnabled__c": true,
        "%vlocity_namespace%__UpsertKey__c": true,
        "IsLocked": false,
        "MayEdit": true,
        "Name": "EOSLoadPricingPricelistEntries",
        "VlocityDataPackType": "SObject",
        "VlocityRecordSObjectType": "%vlocity_namespace%__DRMapItem__c"
    },
    {
        "%vlocity_namespace%__DomainObjectAPIName__c": "%vlocity_namespace%__PriceListEntry__c",
        "%vlocity_namespace%__DomainObjectCreationOrder__c": 1,
        "%vlocity_namespace%__DomainObjectFieldAPIName__c": "%vlocity_namespace%__RulesDescription__c",
        "%vlocity_namespace%__GlobalKey__c": "bb53bf6b-247d-b1ed-a98d-fab7c770196b",
        "%vlocity_namespace%__InterfaceFieldAPIName__c": "Pricing-Pricelist Entries:Context Rule Set",
        "%vlocity_namespace%__IsDisabled__c": false,
        "%vlocity_namespace%__IsRequiredForUpsert__c": false,
        "%vlocity_namespace%__MapId__c": "EOSLoadPricingPricelistEntries7161163355647024",
        "%vlocity_namespace%__OMplusSyncEnabled__c": true,
        "%vlocity_namespace%__UpsertKey__c": false,
        "IsLocked": false,
        "MayEdit": true,
        "Name": "EOSLoadPricingPricelistEntries",
        "VlocityDataPackType": "SObject",
        "VlocityRecordSObjectType": "%vlocity_namespace%__DRMapItem__c"
    },
    {
        "%vlocity_namespace%__DomainObjectAPIName__c": "%vlocity_namespace%__PriceListEntry__c",
        "%vlocity_namespace%__DomainObjectCreationOrder__c": 1,
        "%vlocity_namespace%__DomainObjectFieldAPIName__c": "%vlocity_namespace%__TimePlanId__c",
        "%vlocity_namespace%__GlobalKey__c": "8a7b7243-8711-22bc-4054-4dbfe351ea64",
        "%vlocity_namespace%__InterfaceFieldAPIName__c": "Pricing-Pricelist Entries:Time Plan",
        "%vlocity_namespace%__IsDisabled__c": false,
        "%vlocity_namespace%__IsRequiredForUpsert__c": false,
        "%vlocity_namespace%__LookupDomainObjectFieldName__c": "Name",
        "%vlocity_namespace%__LookupDomainObjectName__c": "%vlocity_namespace%__TimePlan__c",
        "%vlocity_namespace%__LookupDomainObjectRequestedFieldName__c": "Id",
        "%vlocity_namespace%__MapId__c": "EOSLoadPricingPricelistEntries8977807912229208",
        "%vlocity_namespace%__OMplusSyncEnabled__c": true,
        "%vlocity_namespace%__UpsertKey__c": false,
        "IsLocked": false,
        "MayEdit": true,
        "Name": "EOSLoadPricingPricelistEntries",
        "VlocityDataPackType": "SObject",
        "VlocityRecordSObjectType": "%vlocity_namespace%__DRMapItem__c"
    },
    {
        "%vlocity_namespace%__DomainObjectAPIName__c": "%vlocity_namespace%__PriceListEntry__c",
        "%vlocity_namespace%__DomainObjectCreationOrder__c": 1,
        "%vlocity_namespace%__DomainObjectFieldAPIName__c": "%vlocity_namespace%__TimePolicyId__c",
        "%vlocity_namespace%__GlobalKey__c": "2dce480a-592b-de35-2390-ee09769d1646",
        "%vlocity_namespace%__InterfaceFieldAPIName__c": "Pricing-Pricelist Entries:Time Policy",
        "%vlocity_namespace%__IsDisabled__c": false,
        "%vlocity_namespace%__IsRequiredForUpsert__c": false,
        "%vlocity_namespace%__LookupDomainObjectFieldName__c": "Name",
        "%vlocity_namespace%__LookupDomainObjectName__c": "%vlocity_namespace%__TimePolicy__c",
        "%vlocity_namespace%__LookupDomainObjectRequestedFieldName__c": "Id",
        "%vlocity_namespace%__MapId__c": "EOSLoadPricingPricelistEntries009726323643618473",
        "%vlocity_namespace%__OMplusSyncEnabled__c": true,
        "%vlocity_namespace%__UpsertKey__c": false,
        "IsLocked": false,
        "MayEdit": true,
        "Name": "EOSLoadPricingPricelistEntries",
        "VlocityDataPackType": "SObject",
        "VlocityRecordSObjectType": "%vlocity_namespace%__DRMapItem__c"
    },
    {
        "%vlocity_namespace%__ConfigurationValue__c": "FAKEMAPPING",
        "%vlocity_namespace%__DomainObjectAPIName__c": "%vlocity_namespace%__PriceListEntry__c",
        "%vlocity_namespace%__DomainObjectCreationOrder__c": 1,
        "%vlocity_namespace%__DomainObjectFieldAPIName__c": "Id",
        "%vlocity_namespace%__FilterOperator__c": "=",
        "%vlocity_namespace%__GlobalKey__c": "1693b481-7c15-6da8-dd30-6a59c70c30ac",
        "%vlocity_namespace%__IsDisabled__c": true,
        "%vlocity_namespace%__IsRequiredForUpsert__c": false,
        "%vlocity_namespace%__MapId__c": "EOSLoadPricingPricelistEntries6515021628605502",
        "%vlocity_namespace%__OMplusSyncEnabled__c": true,
        "%vlocity_namespace%__UpsertKey__c": false,
        "IsLocked": false,
        "MayEdit": true,
        "Name": "EOSLoadPricingPricelistEntries",
        "VlocityDataPackType": "SObject",
        "VlocityRecordSObjectType": "%vlocity_namespace%__DRMapItem__c"
    },
    {
        "%vlocity_namespace%__DomainObjectAPIName__c": "%vlocity_namespace%__PriceListEntry__c",
        "%vlocity_namespace%__DomainObjectCreationOrder__c": 1,
        "%vlocity_namespace%__DomainObjectFieldAPIName__c": "eos_Application_Version__c",
        "%vlocity_namespace%__GlobalKey__c": "73fc66c0-bff5-451d-4aff-237080382381",
        "%vlocity_namespace%__InterfaceFieldAPIName__c": "Transaction Details:Application Version",
        "%vlocity_namespace%__IsDisabled__c": false,
        "%vlocity_namespace%__IsRequiredForUpsert__c": false,
        "%vlocity_namespace%__MapId__c": "EOSLoadPricingPricelistEntries1436851622955495",
        "%vlocity_namespace%__OMplusSyncEnabled__c": true,
        "%vlocity_namespace%__UpsertKey__c": false,
        "IsLocked": false,
        "MayEdit": true,
        "Name": "EOSLoadPricingPricelistEntries",
        "VlocityDataPackType": "SObject",
        "VlocityRecordSObjectType": "%vlocity_namespace%__DRMapItem__c"
    },
    {
        "%vlocity_namespace%__DomainObjectAPIName__c": "%vlocity_namespace%__PriceListEntry__c",
        "%vlocity_namespace%__DomainObjectCreationOrder__c": 1,
        "%vlocity_namespace%__DomainObjectFieldAPIName__c": "eos_Last_Executed_By__c",
        "%vlocity_namespace%__GlobalKey__c": "1a231b45-6113-f035-8f87-b6f4573b71d7",
        "%vlocity_namespace%__InterfaceFieldAPIName__c": "Transaction Details:Executed By",
        "%vlocity_namespace%__IsDisabled__c": false,
        "%vlocity_namespace%__IsRequiredForUpsert__c": false,
        "%vlocity_namespace%__MapId__c": "EOSLoadPricingPricelistEntries019019904951004918",
        "%vlocity_namespace%__OMplusSyncEnabled__c": true,
        "%vlocity_namespace%__UpsertKey__c": false,
        "IsLocked": false,
        "MayEdit": true,
        "Name": "EOSLoadPricingPricelistEntries",
        "VlocityDataPackType": "SObject",
        "VlocityRecordSObjectType": "%vlocity_namespace%__DRMapItem__c"
    },
    {
        "%vlocity_namespace%__DomainObjectAPIName__c": "%vlocity_namespace%__PriceListEntry__c",
        "%vlocity_namespace%__DomainObjectCreationOrder__c": 1,
        "%vlocity_namespace%__DomainObjectFieldAPIName__c": "eos_Spreadsheet_Name__c",
        "%vlocity_namespace%__GlobalKey__c": "dace4b60-24b3-eb59-5485-432ca979ff7f",
        "%vlocity_namespace%__InterfaceFieldAPIName__c": "Transaction Details:Spreadsheet Name",
        "%vlocity_namespace%__IsDisabled__c": false,
        "%vlocity_namespace%__IsRequiredForUpsert__c": false,
        "%vlocity_namespace%__MapId__c": "EOSLoadPricingPricelistEntries47032050436255224",
        "%vlocity_namespace%__OMplusSyncEnabled__c": true,
        "%vlocity_namespace%__UpsertKey__c": false,
        "IsLocked": false,
        "MayEdit": true,
        "Name": "EOSLoadPricingPricelistEntries",
        "VlocityDataPackType": "SObject",
        "VlocityRecordSObjectType": "%vlocity_namespace%__DRMapItem__c"
    },
    {
        "%vlocity_namespace%__DomainObjectAPIName__c": "%vlocity_namespace%__PriceListEntry__c",
        "%vlocity_namespace%__DomainObjectCreationOrder__c": 1,
        "%vlocity_namespace%__DomainObjectFieldAPIName__c": "eos_Spreadsheet_URL__c",
        "%vlocity_namespace%__GlobalKey__c": "89ca88f0-576e-166a-a725-b4333fceb7ac",
        "%vlocity_namespace%__InterfaceFieldAPIName__c": "Transaction Details:Spreadsheet URL",
        "%vlocity_namespace%__IsDisabled__c": false,
        "%vlocity_namespace%__IsRequiredForUpsert__c": false,
        "%vlocity_namespace%__MapId__c": "EOSLoadPricingPricelistEntries19825605231795418",
        "%vlocity_namespace%__OMplusSyncEnabled__c": true,
        "%vlocity_namespace%__UpsertKey__c": false,
        "IsLocked": false,
        "MayEdit": true,
        "Name": "EOSLoadPricingPricelistEntries",
        "VlocityDataPackType": "SObject",
        "VlocityRecordSObjectType": "%vlocity_namespace%__DRMapItem__c"
    },
    {
        "%vlocity_namespace%__DomainObjectAPIName__c": "%vlocity_namespace%__PriceListEntry__c",
        "%vlocity_namespace%__DomainObjectCreationOrder__c": 1,
        "%vlocity_namespace%__DomainObjectFieldAPIName__c": "eos_Transaction_ID__c",
        "%vlocity_namespace%__GlobalKey__c": "5707e524-51e4-7928-9cc3-f4a1ab755252",
        "%vlocity_namespace%__InterfaceFieldAPIName__c": "Transaction Details:Transaction ID",
        "%vlocity_namespace%__IsDisabled__c": false,
        "%vlocity_namespace%__IsRequiredForUpsert__c": false,
        "%vlocity_namespace%__MapId__c": "EOSLoadPricingPricelistEntries9011599626761193",
        "%vlocity_namespace%__OMplusSyncEnabled__c": true,
        "%vlocity_namespace%__UpsertKey__c": false,
        "IsLocked": false,
        "MayEdit": true,
        "Name": "EOSLoadPricingPricelistEntries",
        "VlocityDataPackType": "SObject",
        "VlocityRecordSObjectType": "%vlocity_namespace%__DRMapItem__c"
    },
    {
        "%vlocity_namespace%__DomainObjectAPIName__c": "%vlocity_namespace%__PriceListEntry__c",
        "%vlocity_namespace%__DomainObjectCreationOrder__c": 1,
        "%vlocity_namespace%__DomainObjectFieldAPIName__c": "eos_Transaction_Timestamp__c",
        "%vlocity_namespace%__GlobalKey__c": "8fdc1255-a8a5-702f-baea-95e9f397993c",
        "%vlocity_namespace%__InterfaceFieldAPIName__c": "Transaction Details:Transaction Timestamp",
        "%vlocity_namespace%__IsDisabled__c": false,
        "%vlocity_namespace%__IsRequiredForUpsert__c": false,
        "%vlocity_namespace%__MapId__c": "EOSLoadPricingPricelistEntries6552939953757084",
        "%vlocity_namespace%__OMplusSyncEnabled__c": true,
        "%vlocity_namespace%__UpsertKey__c": false,
        "IsLocked": false,
        "MayEdit": true,
        "Name": "EOSLoadPricingPricelistEntries",
        "VlocityDataPackType": "SObject",
        "VlocityRecordSObjectType": "%vlocity_namespace%__DRMapItem__c"
    },
    {
        "%vlocity_namespace%__ConfigurationValue__c": "FAKEMAPPING",
        "%vlocity_namespace%__DomainObjectAPIName__c": "%vlocity_namespace%__RuleAssignment__c",
        "%vlocity_namespace%__DomainObjectCreationOrder__c": 2,
        "%vlocity_namespace%__DomainObjectFieldAPIName__c": "%vlocity_namespace%__ObjectId__c",
        "%vlocity_namespace%__FilterOperator__c": "=",
        "%vlocity_namespace%__GlobalKey__c": "9432693b-2280-5460-0d93-ac8aef7191d3",
        "%vlocity_namespace%__IsDisabled__c": false,
        "%vlocity_namespace%__IsRequiredForUpsert__c": true,
        "%vlocity_namespace%__LinkCreatedField__c": "Id",
        "%vlocity_namespace%__LinkCreatedIndex__c": 1,
        "%vlocity_namespace%__MapId__c": "EOSLoadPricingPricelistEntries22716194173764737",
        "%vlocity_namespace%__OMplusSyncEnabled__c": true,
        "%vlocity_namespace%__UpsertKey__c": true,
        "IsLocked": false,
        "MayEdit": true,
        "Name": "EOSLoadPricingPricelistEntries",
        "VlocityDataPackType": "SObject",
        "VlocityRecordSObjectType": "%vlocity_namespace%__DRMapItem__c"
    },
    {
        "%vlocity_namespace%__DomainObjectAPIName__c": "%vlocity_namespace%__RuleAssignment__c",
        "%vlocity_namespace%__DomainObjectCreationOrder__c": 2,
        "%vlocity_namespace%__DomainObjectFieldAPIName__c": "%vlocity_namespace%__RuleId__c",
        "%vlocity_namespace%__GlobalKey__c": "7e7cdc8b-5048-c5cd-211f-fa053cd2591b",
        "%vlocity_namespace%__InterfaceFieldAPIName__c": "Pricing-Pricelist Entries:Qualification Context Rule Set",
        "%vlocity_namespace%__IsDisabled__c": false,
        "%vlocity_namespace%__IsRequiredForUpsert__c": true,
        "%vlocity_namespace%__LookupDomainObjectFieldName__c": "Name",
        "%vlocity_namespace%__LookupDomainObjectName__c": "%vlocity_namespace%__Rule__c",
        "%vlocity_namespace%__LookupDomainObjectRequestedFieldName__c": "Id",
        "%vlocity_namespace%__MapId__c": "EOSLoadPricingPricelistEntries5817054552262062",
        "%vlocity_namespace%__OMplusSyncEnabled__c": true,
        "%vlocity_namespace%__UpsertKey__c": true,
        "IsLocked": false,
        "MayEdit": true,
        "Name": "EOSLoadPricingPricelistEntries",
        "VlocityDataPackType": "SObject",
        "VlocityRecordSObjectType": "%vlocity_namespace%__DRMapItem__c"
    },
    {
        "%vlocity_namespace%__ConfigurationValue__c": "FAKEMAPPING",
        "%vlocity_namespace%__DomainObjectAPIName__c": "%vlocity_namespace%__RuleAssignment__c",
        "%vlocity_namespace%__DomainObjectCreationOrder__c": 2,
        "%vlocity_namespace%__DomainObjectFieldAPIName__c": "Id",
        "%vlocity_namespace%__FilterOperator__c": "=",
        "%vlocity_namespace%__GlobalKey__c": "cd083b17-b1d5-8f58-9a9f-9d038e723619",
        "%vlocity_namespace%__IsDisabled__c": true,
        "%vlocity_namespace%__IsRequiredForUpsert__c": false,
        "%vlocity_namespace%__MapId__c": "EOSLoadPricingPricelistEntries39586112443542865",
        "%vlocity_namespace%__OMplusSyncEnabled__c": true,
        "%vlocity_namespace%__UpsertKey__c": false,
        "IsLocked": false,
        "MayEdit": true,
        "Name": "EOSLoadPricingPricelistEntries",
        "VlocityDataPackType": "SObject",
        "VlocityRecordSObjectType": "%vlocity_namespace%__DRMapItem__c"
    },
    {
        "%vlocity_namespace%__DomainObjectAPIName__c": "%vlocity_namespace%__RuleAssignment__c",
        "%vlocity_namespace%__DomainObjectCreationOrder__c": 2,
        "%vlocity_namespace%__DomainObjectFieldAPIName__c": "Name",
        "%vlocity_namespace%__GlobalKey__c": "9e6f53e0-acda-f646-654a-953decea4952",
        "%vlocity_namespace%__InterfaceFieldAPIName__c": "Pricing-Pricelist Entries:Qualification Context Rule Set Assignment Name",
        "%vlocity_namespace%__IsDisabled__c": false,
        "%vlocity_namespace%__IsRequiredForUpsert__c": false,
        "%vlocity_namespace%__MapId__c": "EOSLoadPricingPricelistEntries11794542500196736",
        "%vlocity_namespace%__OMplusSyncEnabled__c": true,
        "%vlocity_namespace%__UpsertKey__c": false,
        "IsLocked": false,
        "MayEdit": true,
        "Name": "EOSLoadPricingPricelistEntries",
        "VlocityDataPackType": "SObject",
        "VlocityRecordSObjectType": "%vlocity_namespace%__DRMapItem__c"
    }
]